pyappi/__init__.py
pyappi/api_base.py
pyappi/client_cli.py
pyappi/endpoints.py
pyappi/server_cli.py
pyappi/websock.py
pyappi/block/__init__.py
pyappi/block/block.py
pyappi/block/endpoints.py
pyappi/client/__init__.py
pyappi/client/cached_document.py
pyappi/client/client_handle.py
pyappi/client/config.py
pyappi/client/lock.py
pyappi/client/realtime_document.py
pyappi/client/session.py
pyappi/client/sync.py
pyappi/document/__init__.py
pyappi/document/access.py
pyappi/document/delta.py
pyappi/document/document.py
pyappi/document/documentold.py
pyappi/document/endpoints.py
pyappi/document/enumeration.py
pyappi/document/exceptions.py
pyappi/document/file_handler.py
pyappi/document/history.py
pyappi/document/local.py
pyappi/document/lock.py
pyappi/document/merge.py
pyappi/document/random_handler.py
pyappi/document/rules.py
pyappi/document/transaction.py
pyappi/document/transactionold.py
pyappi/document/type.py
pyappi/document/volatile_document.py
pyappi/encoding/__init__.py
pyappi/encoding/url.py
pyappi/events/__init__.py
pyappi/events/events.py
pyappi/logs/__init__.py
pyappi/logs/log_handler.py
pyappi/service/__init__.py
pyappi/service/endpoints.py
pyappi/service/service.py
pyappi/service/session.py
pyappi/stats/__init__.py
pyappi/stats/endpoints.py
pyappi/stats/stats.py
pyappi/stats/stats_handler.py
pyappi/sync/__init__.py
pyappi/sync/endpoints.py
pyappi/user/__init__.py
pyappi/user/endpoints.py
pyappi/user/session.py
pyappi/util/__init__.py
pyappi/util/filename.py
pyappi/util/interval.py
pyappi/util/login.py
pyappi/util/merge.py
pyappi/util/super_lock.py
tests/__init__.py
tests/test_blind_write.py
tests/test_block.py
tests/test_core.py
tests/test_events.py
tests/test_inherit_permissions.py
tests/test_log.py
tests/test_sync.py
tests/test_tally.py
pyappi-1.3.6.dist-info/LICENSE
pyappi-1.3.6.dist-info/METADATA
pyappi-1.3.6.dist-info/WHEEL
pyappi-1.3.6.dist-info/entry_points.txt
pyappi-1.3.6.dist-info/top_level.txt
pyappi-1.3.6.dist-info/RECORD
